aiobroadlink/__init__.py
aiobroadlink/__main__.py
aiobroadlink/aiobroadlink.py
aiobroadlink-0.1.3.dist-info/LICENSE
aiobroadlink-0.1.3.dist-info/METADATA
aiobroadlink-0.1.3.dist-info/WHEEL
aiobroadlink-0.1.3.dist-info/entry_points.txt
aiobroadlink-0.1.3.dist-info/top_level.txt
aiobroadlink-0.1.3.dist-info/RECORD
