Metadata-Version: 2.1
Name: aiobroadlink
Version: 0.1.3
Summary: Pure Python library to control/provision Broadlink devices
Home-page: https://github.com/frawau/aiobroadlink
Author: François Wautier.
Author-email: francois@wautier.eu
License: MIT
Keywords: Broadlink,IoT,WiFi,Home Automation,asyncio
Platform: unix
Platform: linux
Platform: osx
Classifier: Development Status :: 4 - Beta
Classifier: Intended Audience :: Developers
Classifier: Intended Audience :: System Administrators
Classifier: License :: OSI Approved :: MIT License
Classifier: Operating System :: POSIX
Classifier: Operating System :: POSIX :: Linux
Classifier: Operating System :: MacOS :: MacOS X
Classifier: Topic :: Software Development :: Libraries
Classifier: Programming Language :: Python
Classifier: Programming Language :: Python :: 3.5
Classifier: Programming Language :: Python :: 3.6
Classifier: Programming Language :: Python :: 3.7
Classifier: Programming Language :: Python :: Implementation :: CPython
Requires-Dist: cryptography (>=2.8)
